neuro_admin_client/__init__.py
neuro_admin_client/admin_client.py
neuro_admin_client/auth_client.py
neuro_admin_client/bearer_auth.py
neuro_admin_client/entities.py
neuro_admin_client/py.typed
neuro_admin_client/security.py
neuro_admin_client-25.12.0.dist-info/METADATA
neuro_admin_client-25.12.0.dist-info/WHEEL
neuro_admin_client-25.12.0.dist-info/licenses/LICENSE
neuro_admin_client-25.12.0.dist-info/RECORD
