Metadata-Version: 2.4
Name: neuro-admin-client
Version: 25.12.0
Summary: Internal client for Neu.ro admin service
Author-email: Andrew Svetlov <andrew.svetlov@gmail.com>
License-Expression: Apache-2.0
License-File: LICENSE
Classifier: License :: OSI Approved :: Apache Software License
Classifier: Programming Language :: Python :: 3
Requires-Python: >=3.10
Requires-Dist: aiohttp-security>=0.4.0
Requires-Dist: aiohttp[speedups]>=3.11.3
Requires-Dist: multidict>=6
Requires-Dist: python-jose>=3.0.1
Requires-Dist: typing-extensions>=4.15.0
Requires-Dist: yarl>=1.22
